.gitignore
LICENSE.txt
README.md
setup.cfg
setup.py
data/luxembourg.README.txt
data/luxembourg.wkt
doc/howto-publish.txt
geetiles/__init__.py
geetiles/cmds.py
geetiles/gee.py
geetiles/main.py
geetiles/partitions.py
geetiles/utils.py
geetiles.egg-info/PKG-INFO
geetiles.egg-info/SOURCES.txt
geetiles.egg-info/dependency_links.txt
geetiles.egg-info/entry_points.txt
geetiles.egg-info/not-zip-safe
geetiles.egg-info/requires.txt
geetiles.egg-info/top_level.txt
geetiles/data/natural_earth.parquet
geetiles/defs/canadacrop2020.py
geetiles/defs/esaworldcover.py
geetiles/defs/firecci51.py
geetiles/defs/globalfloods.py
geetiles/defs/humanpop2015.py
geetiles/defs/modis44b006veg.py
geetiles/defs/s1count.py
geetiles/defs/s1grd.py
geetiles/defs/s1grdm.py
geetiles/defs/s1grdobs.py
geetiles/defs/s2.py
geetiles/defs/s2_13bands.py
geetiles/defs/s2_raw.py
geetiles/defs/s2rgb.py
geetiles/defs/s2rgbm.py
geetiles/defs/sentinel2rgbmedian2020.py
geetiles/defs/soilphbenelux.py
geetiles/defs/soilphcolombia.py
geetiles/defs/srtm.py
geetiles/defs/treecover2020.py
geetiles/defs/usnedlandforms.py
imgs/dataframe.png
imgs/landcover.png
imgs/luxembourg-bands-communes.png
imgs/luxembourg-bands.png
imgs/luxembourg-communes-random5k.png
imgs/luxembourg-communes.png
imgs/luxembourg-random-5k.png
imgs/luxembourg-splits.png
imgs/luxgrid.png
imgs/sentinel2.png