Metadata-Version: 2.1
Name: geetiles
Version: 0.1.7
Summary: download Google Earth Engine datasets to tiles as geotiff arrays
Home-page: https://github.com/rramosp/geetiles
Author: raul ramos
Author-email: raul.ramos@udea.edu.co
License-File: LICENSE.txt
Requires-Dist: matplotlib
Requires-Dist: numpy
Requires-Dist: pandas
Requires-Dist: joblib
Requires-Dist: progressbar2
Requires-Dist: psutil
Requires-Dist: scipy
Requires-Dist: shapely
Requires-Dist: geopandas
Requires-Dist: pyproj
Requires-Dist: rasterio
Requires-Dist: retry
Requires-Dist: earthengine-api
Requires-Dist: alphashape
Requires-Dist: scikit-image
